<?xml version="1.0" encoding="UTF-8"?>
<qes:espresso xsi:schemaLocation="http://www.quantum-espresso.org/ns/qes/qes-1.0 http://www.quantum-espresso.org/ns/qes/qes_220603.xsd" Units="Hartree atomic units" xmlns:xsi="http://www.w3.org/2001/XMLSchema-instance" xmlns:qes="http://www.quantum-espresso.org/ns/qes/qes-1.0">
  <!--All quantities are in Hartree atomic units unless otherwise specified-->
  <general_info>
    <xml_format NAME="QEXSD" VERSION="21.11.01">QEXSD_21.11.01</xml_format>
    <creator NAME="PWSCF" VERSION="7.1">XML file generated by PWSCF</creator>
    <created DATE="20Oct2022" TIME="17:22:39">This run was terminated on:  17:22:39  20 Oct 2022</created>
    <job></job>
  </general_info>
  <parallel_info>
    <nprocs>1</nprocs>
    <nthreads>1</nthreads>
    <ntasks>1</ntasks>
    <nbgrp>1</nbgrp>
    <npool>1</npool>
    <ndiag>1</ndiag>
  </parallel_info>
  <input>
    <control_variables>
      <title></title>
      <calculation>scf</calculation>
      <restart_mode>from_scratch</restart_mode>
      <prefix>hBN_water_Oup_Hdown</prefix>
      <pseudo_dir>.</pseudo_dir>
      <outdir>.</outdir>
      <stress>false</stress>
      <forces>false</forces>
      <wf_collect>true</wf_collect>
      <disk_io>low</disk_io>
      <max_seconds>10000000</max_seconds>
      <nstep>1</nstep>
      <etot_conv_thr>5.000000000000000e-5</etot_conv_thr>
      <forc_conv_thr>5.000000000000000e-4</forc_conv_thr>
      <press_conv_thr>5.000000000000000e-1</press_conv_thr>
      <verbosity>low</verbosity>
      <print_every>100000</print_every>
      <fcp>false</fcp>
      <rism>false</rism>
    </control_variables>
    <atomic_species ntyp="4">
      <species name="B">
        <mass>1.081100000000000e1</mass>
        <pseudo_file>B.pbe-n-kjpaw_psl.1.0.0.UPF</pseudo_file>
      </species>
      <species name="N">
        <mass>1.400670000000000e1</mass>
        <pseudo_file>N.pbe-n-kjpaw_psl.1.0.0.UPF</pseudo_file>
      </species>
      <species name="O">
        <mass>1.599900000000000e1</mass>
        <pseudo_file>O.pbe-n-kjpaw_psl.1.0.0.UPF</pseudo_file>
      </species>
      <species name="H">
        <mass>1.007840000000000e0</mass>
        <pseudo_file>H.pbe-kjpaw_psl.1.0.0.UPF</pseudo_file>
      </species>
    </atomic_species>
    <atomic_structure nat="11" alat="9.465808233602e0">
      <atomic_positions>
        <atom name="B" index="1">7.099356175201274e0 1.366274728207313e0 1.133835674775462e1</atom>
        <atom name="B" index="2">2.366452058400425e0 1.366274728207313e0 1.133835674775462e1</atom>
        <atom name="B" index="3">0.000000000000000e0 5.465090692520608e0 1.133835674775462e1</atom>
        <atom name="B" index="4">4.732904116800849e0 5.465090692520608e0 1.133835674775462e1</atom>
        <atom name="N" index="5">7.099356175201274e0 6.831357200419279e0 1.133835674775462e1</atom>
        <atom name="N" index="6">2.366452058400425e0 6.831357200419279e0 1.133835674775462e1</atom>
        <atom name="N" index="7">0.000000000000000e0 2.732541236105983e0 1.133835674775462e1</atom>
        <atom name="N" index="8">4.732904116800849e0 2.732541236105983e0 1.133835674775462e1</atom>
        <atom name="O" index="9">0.000000000000000e0 0.000000000000000e0 1.776340667422100e1</atom>
        <atom name="H" index="10">0.000000000000000e0 1.430429380562935e0 1.665627282958650e1</atom>
        <atom name="H" index="11">0.000000000000000e0 6.767202548063656e0 1.665627282958650e1</atom>
      </atomic_positions>
      <cell>
        <a1>9.465808233601699e0 0.000000000000000e0 0.000000000000000e0</a1>
        <a2>0.000000000000000e0 8.197631928626592e0 0.000000000000000e0</a2>
        <a3>0.000000000000000e0 0.000000000000000e0 5.669178373877311e1</a3>
      </cell>
    </atomic_structure>
    <dft>
      <functional>PBE</functional>
    </dft>
    <spin>
      <lsda>false</lsda>
      <noncolin>false</noncolin>
      <spinorbit>false</spinorbit>
    </spin>
    <bands>
      <nbnd>33</nbnd>
      <tot_charge>0.000000000000000e0</tot_charge>
      <occupations>fixed</occupations>
    </bands>
    <basis>
      <gamma_only>false</gamma_only>
      <ecutwfc>1.469972352000000e1</ecutwfc>
      <ecutrho>5.879889408000000e1</ecutrho>
    </basis>
    <electron_control>
      <diagonalization>davidson</diagonalization>
      <mixing_mode>plain</mixing_mode>
      <mixing_beta>7.000000000000000e-1</mixing_beta>
      <conv_thr>5.000000000000000e-7</conv_thr>
      <mixing_ndim>8</mixing_ndim>
      <max_nstep>100</max_nstep>
      <real_space_q>false</real_space_q>
      <real_space_beta>false</real_space_beta>
      <tq_smoothing>false</tq_smoothing>
      <tbeta_smoothing>false</tbeta_smoothing>
      <diago_thr_init>0.000000000000000e0</diago_thr_init>
      <diago_full_acc>false</diago_full_acc>
      <diago_cg_maxiter>20</diago_cg_maxiter>
      <diago_ppcg_maxiter>20</diago_ppcg_maxiter>
      <diago_rmm_ndim>4</diago_rmm_ndim>
      <diago_gs_nblock>16</diago_gs_nblock>
      <diago_rmm_conv>false</diago_rmm_conv>
    </electron_control>
    <k_points_IBZ>
      <monkhorst_pack nk1="1" nk2="1" nk3="1" k1="0" k2="0" k3="0">Monkhorst-Pack</monkhorst_pack>
    </k_points_IBZ>
    <ion_control>
      <ion_dynamics>none</ion_dynamics>
      <upscale>1.000000000000000e2</upscale>
      <remove_rigid_rot>false</remove_rigid_rot>
      <refold_pos>false</refold_pos>
    </ion_control>
    <cell_control>
      <cell_dynamics>none</cell_dynamics>
      <pressure>0.000000000000000e0</pressure>
      <wmass>1.172854800000000e2</wmass>
      <cell_do_free>all</cell_do_free>
    </cell_control>
    <symmetry_flags>
      <nosym>false</nosym>
      <nosym_evc>false</nosym_evc>
      <noinv>false</noinv>
      <no_t_rev>false</no_t_rev>
      <force_symmorphic>false</force_symmorphic>
      <use_all_frac>false</use_all_frac>
    </symmetry_flags>
  </input>
  <output>
    <convergence_info>
      <scf_conv>
        <convergence_achieved>true</convergence_achieved>
        <n_scf_steps>9</n_scf_steps>
        <scf_error>7.436289210992096e-8</scf_error>
      </scf_conv>
    </convergence_info>
    <algorithmic_info>
      <real_space_q>false</real_space_q>
      <real_space_beta>false</real_space_beta>
      <uspp>true</uspp>
      <paw>true</paw>
    </algorithmic_info>
    <atomic_species ntyp="4" pseudo_dir="./">
      <species name="B">
        <mass>1.081100000000000e1</mass>
        <pseudo_file>B.pbe-n-kjpaw_psl.1.0.0.UPF</pseudo_file>
      </species>
      <species name="N">
        <mass>1.400670000000000e1</mass>
        <pseudo_file>N.pbe-n-kjpaw_psl.1.0.0.UPF</pseudo_file>
      </species>
      <species name="O">
        <mass>1.599900000000000e1</mass>
        <pseudo_file>O.pbe-n-kjpaw_psl.1.0.0.UPF</pseudo_file>
      </species>
      <species name="H">
        <mass>1.007840000000000e0</mass>
        <pseudo_file>H.pbe-kjpaw_psl.1.0.0.UPF</pseudo_file>
      </species>
    </atomic_species>
    <atomic_structure nat="11" alat="9.465808233602e0">
      <atomic_positions>
        <atom name="B" index="1">7.099356175201274e0 1.366274728207313e0 1.133835674775462e1</atom>
        <atom name="B" index="2">2.366452058400425e0 1.366274728207313e0 1.133835674775462e1</atom>
        <atom name="B" index="3">0.000000000000000e0 5.465090692520608e0 1.133835674775462e1</atom>
        <atom name="B" index="4">4.732904116800849e0 5.465090692520608e0 1.133835674775462e1</atom>
        <atom name="N" index="5">7.099356175201274e0 6.831357200419279e0 1.133835674775462e1</atom>
        <atom name="N" index="6">2.366452058400425e0 6.831357200419279e0 1.133835674775462e1</atom>
        <atom name="N" index="7">0.000000000000000e0 2.732541236105983e0 1.133835674775462e1</atom>
        <atom name="N" index="8">4.732904116800849e0 2.732541236105983e0 1.133835674775462e1</atom>
        <atom name="O" index="9">0.000000000000000e0 0.000000000000000e0 1.776340667422100e1</atom>
        <atom name="H" index="10">0.000000000000000e0 1.430429380562935e0 1.665627282958650e1</atom>
        <atom name="H" index="11">0.000000000000000e0 6.767202548063656e0 1.665627282958650e1</atom>
      </atomic_positions>
      <cell>
        <a1>9.465808233601699e0 0.000000000000000e0 0.000000000000000e0</a1>
        <a2>0.000000000000000e0 8.197631928626592e0 0.000000000000000e0</a2>
        <a3>0.000000000000000e0 0.000000000000000e0 5.669178373877311e1</a3>
      </cell>
    </atomic_structure>
    <symmetries>
      <nsym>2</nsym>
      <nrot>8</nrot>
      <space_group>0</space_group>
      <symmetry>
        <info name="identity">crystal_symmetry</info>
        <rotation rank="2" dims="3 3">
          1.000000000000000e0 0.000000000000000e0 0.000000000000000e0
          0.000000000000000e0 1.000000000000000e0 0.000000000000000e0
          0.000000000000000e0 0.000000000000000e0 1.000000000000000e0
          </rotation>
        <fractional_translation>0.000000000000000e0 0.000000000000000e0 0.000000000000000e0</fractional_translation>
        <equivalent_atoms size="11" nat="11">
          1 2 3 4 5 6 7 8
          9 10 11
          </equivalent_atoms>
      </symmetry>
      <symmetry>
        <info name="inv. 180 deg rotation - cart. axis [1,0,0]">crystal_symmetry</info>
        <rotation rank="2" dims="3 3">
          -1.000000000000000e0 0.000000000000000e0 0.000000000000000e0
          0.000000000000000e0 1.000000000000000e0 0.000000000000000e0
          0.000000000000000e0 0.000000000000000e0 1.000000000000000e0
          </rotation>
        <fractional_translation>0.000000000000000e0 0.000000000000000e0 0.000000000000000e0</fractional_translation>
        <equivalent_atoms size="11" nat="11">
          2 1 3 4 6 5 7 8
          9 10 11
          </equivalent_atoms>
      </symmetry>
      <symmetry>
        <info name="180 deg rotation - cart. axis [0,1,0]">lattice_symmetry</info>
        <rotation rank="2" dims="3 3">
          -1.000000000000000e0 0.000000000000000e0 0.000000000000000e0
          0.000000000000000e0 1.000000000000000e0 0.000000000000000e0
          0.000000000000000e0 0.000000000000000e0 -1.000000000000000e0
          </rotation>
      </symmetry>
      <symmetry>
        <info name="180 deg rotation - cart. axis [1,0,0]">lattice_symmetry</info>
        <rotation rank="2" dims="3 3">
          1.000000000000000e0 0.000000000000000e0 0.000000000000000e0
          0.000000000000000e0 -1.000000000000000e0 0.000000000000000e0
          0.000000000000000e0 0.000000000000000e0 -1.000000000000000e0
          </rotation>
      </symmetry>
      <symmetry>
        <info name="inversion">lattice_symmetry</info>
        <rotation rank="2" dims="3 3">
          -1.000000000000000e0 0.000000000000000e0 0.000000000000000e0
          0.000000000000000e0 -1.000000000000000e0 0.000000000000000e0
          0.000000000000000e0 0.000000000000000e0 -1.000000000000000e0
          </rotation>
      </symmetry>
      <symmetry>
        <info name="inv. 180 deg rotation - cart. axis [0,0,1]">lattice_symmetry</info>
        <rotation rank="2" dims="3 3">
          1.000000000000000e0 0.000000000000000e0 0.000000000000000e0
          0.000000000000000e0 1.000000000000000e0 0.000000000000000e0
          0.000000000000000e0 0.000000000000000e0 -1.000000000000000e0
          </rotation>
      </symmetry>
      <symmetry>
        <info name="inv. 180 deg rotation - cart. axis [0,1,0]">lattice_symmetry</info>
        <rotation rank="2" dims="3 3">
          1.000000000000000e0 0.000000000000000e0 0.000000000000000e0
          0.000000000000000e0 -1.000000000000000e0 0.000000000000000e0
          0.000000000000000e0 0.000000000000000e0 1.000000000000000e0
          </rotation>
      </symmetry>
      <symmetry>
        <info name="180 deg rotation - cart. axis [0,0,1]">lattice_symmetry</info>
        <rotation rank="2" dims="3 3">
          -1.000000000000000e0 0.000000000000000e0 0.000000000000000e0
          0.000000000000000e0 -1.000000000000000e0 0.000000000000000e0
          0.000000000000000e0 0.000000000000000e0 1.000000000000000e0
          </rotation>
      </symmetry>
    </symmetries>
    <basis_set>
      <gamma_only>false</gamma_only>
      <ecutwfc>1.469972352000000e1</ecutwfc>
      <ecutrho>5.879889408000000e1</ecutrho>
      <fft_grid nr1="36" nr2="30" nr3="200"></fft_grid>
      <fft_smooth nr1="36" nr2="30" nr3="200"></fft_smooth>
      <fft_box nr1="36" nr2="30" nr3="200"></fft_box>
      <ngm>94803</ngm>
      <ngms>94803</ngms>
      <npwx>11827</npwx>
      <reciprocal_lattice>
        <b1>1.000000000000000e0 0.000000000000000e0 0.000000000000000e0</b1>
        <b2>0.000000000000000e0 1.154700322729368e0 0.000000000000000e0</b2>
        <b3>0.000000000000000e0 0.000000000000000e0 1.669696666666667e-1</b3>
      </reciprocal_lattice>
    </basis_set>
    <dft>
      <functional>PBE</functional>
    </dft>
    <magnetization>
      <lsda>false</lsda>
      <noncolin>false</noncolin>
      <spinorbit>false</spinorbit>
      <absolute>0.000000000000000e0</absolute>
    </magnetization>
    <total_energy>
      <etot>-1.015013541390703e2</etot>
      <eband>-1.836425699145088e1</eband>
      <ehart>4.672466388349568e2</ehart>
      <vtxc>-2.530203455979998e1</vtxc>
      <etxc>-2.211289960375380e1</etxc>
      <ewald>4.113572594830086e2</ewald>
    </total_energy>
    <band_structure>
      <lsda>false</lsda>
      <noncolin>false</noncolin>
      <spinorbit>false</spinorbit>
      <nbnd>33</nbnd>
      <nelec>4.000000000000000e1</nelec>
      <num_of_atomic_wfc>38</num_of_atomic_wfc>
      <wf_collected>true</wf_collected>
      <fermi_energy>-2.153730229808997e-1</fermi_energy>
      <highestOccupiedLevel>-2.153730229808997e-1</highestOccupiedLevel>
      <lowestUnoccupiedLevel>-6.057614365733267e-2</lowestUnoccupiedLevel>
      <starting_k_points>
        <monkhorst_pack nk1="1" nk2="1" nk3="1" k1="0" k2="0" k3="0">Monkhorst-Pack</monkhorst_pack>
      </starting_k_points>
      <nks>1</nks>
      <occupations_kind>fixed</occupations_kind>
      <ks_energies>
        <k_point weight="2.000000000000e0">0.000000000000000e0 0.000000000000000e0 0.000000000000000e0</k_point>
        <npw>11827</npw>
        <eigenvalues size="33">
          -9.004649503761982e-1 -8.501806850438182e-1 -7.421431821180632e-1 -7.415633684495071e-1 -7.375367447129402e-1
          -5.269855177140528e-1 -4.803848113426480e-1 -4.800698498070176e-1 -4.346477704183636e-1 -4.160844497154909e-1
          -4.157869300083051e-1 -3.933261733437971e-1 -3.518910900123341e-1 -2.960055520707716e-1 -2.458628757838548e-1
          -2.457311297436657e-1 -2.394233181463121e-1 -2.384571856383210e-1 -2.302098882990781e-1 -2.153730229808997e-1
          -6.057614365733267e-2 -3.779942218022878e-2 -2.452084644262293e-2 -1.592160961934974e-2 2.958273284952712e-3
          9.987486635098929e-3 1.078421384067491e-2 1.600086528786711e-2 3.602698758143097e-2 4.740656750480166e-2
          8.137156888331603e-2 9.375950816513917e-2 1.305502617585846e-1
          </eigenvalues>
        <occupations size="33">
          1.000000000000000e0 1.000000000000000e0 1.000000000000000e0 1.000000000000000e0 1.000000000000000e0
          1.000000000000000e0 1.000000000000000e0 1.000000000000000e0 1.000000000000000e0 1.000000000000000e0
          1.000000000000000e0 1.000000000000000e0 1.000000000000000e0 1.000000000000000e0 1.000000000000000e0
          1.000000000000000e0 1.000000000000000e0 1.000000000000000e0 1.000000000000000e0 1.000000000000000e0
          0.000000000000000e0 0.000000000000000e0 0.000000000000000e0 0.000000000000000e0 0.000000000000000e0
          0.000000000000000e0 0.000000000000000e0 0.000000000000000e0 0.000000000000000e0 0.000000000000000e0
          0.000000000000000e0 0.000000000000000e0 0.000000000000000e0
          </occupations>
      </ks_energies>
    </band_structure>
  </output>
  <exit_status>0</exit_status>
  <timing_info>
    <total label="PWSCF">
      <cpu>1.393064700000000e1</cpu>
      <wall>1.438201713562012e1</wall>
    </total>
    <partial label="init_run" calls="1">
      <cpu>2.598376000000000e0</cpu>
      <wall>2.703963994979858e0</wall>
    </partial>
    <partial label="hinit0" calls="1">
      <cpu>1.341663000000000e0</cpu>
      <wall>1.390806913375854e0</wall>
    </partial>
    <partial label="init_vloc" calls="1">
      <cpu>5.801670000000001e-1</cpu>
      <wall>5.802159309387207e-1</wall>
    </partial>
    <partial label="init_us_1" calls="1">
      <cpu>2.441300000000001e-1</cpu>
      <wall>2.441918849945068e-1</wall>
    </partial>
    <partial label="fft" calls="110">
      <cpu>2.453329999999951e-1</cpu>
      <wall>2.867317199707031e-1</wall>
    </partial>
    <partial label="potinit" calls="1">
      <cpu>9.321920000000002e-1</cpu>
      <wall>9.483258724212646e-1</wall>
    </partial>
    <partial label="PAW_symme" calls="19">
      <cpu>3.119999999992018e-4</cpu>
      <wall>3.051757812500000e-4</wall>
    </partial>
    <partial label="v_of_rho" calls="10">
      <cpu>9.849139999999998e-1</cpu>
      <wall>1.001863241195679e0</wall>
    </partial>
    <partial label="v_xc" calls="10">
      <cpu>9.512770000000010e-1</cpu>
      <wall>9.682359695434570e-1</wall>
    </partial>
    <partial label="v_h" calls="10">
      <cpu>3.356100000000062e-2</cpu>
      <wall>3.356671333312988e-2</wall>
    </partial>
    <partial label="PAW_pot" calls="10">
      <cpu>2.509880000000001e0</cpu>
      <wall>2.509999275207520e0</wall>
    </partial>
    <partial label="newd" calls="10">
      <cpu>6.218450000000004e-1</cpu>
      <wall>7.730839252471924e-1</wall>
    </partial>
    <partial label="wfcinit" calls="1">
      <cpu>2.476430000000001e-1</cpu>
      <wall>2.518610954284668e-1</wall>
    </partial>
    <partial label="init_us_2" calls="19">
      <cpu>5.685999999999503e-2</cpu>
      <wall>6.012868881225586e-2</wall>
    </partial>
    <partial label="init_us_2:cp" calls="19">
      <cpu>5.680200000000646e-2</cpu>
      <wall>6.009745597839355e-2</wall>
    </partial>
    <partial label="wfcinit:atom" calls="1">
      <cpu>4.095000000000404e-3</cpu>
      <wall>4.099130630493164e-3</wall>
    </partial>
    <partial label="atomic_wfc" calls="1">
      <cpu>4.087000000000174e-3</cpu>
      <wall>4.095077514648438e-3</wall>
    </partial>
    <partial label="wfcinit:wfcr" calls="1">
      <cpu>2.194080000000000e-1</cpu>
      <wall>2.234048843383789e-1</wall>
    </partial>
    <partial label="wfcrot" calls="1">
      <cpu>2.194050000000001e-1</cpu>
      <wall>2.234029769897461e-1</wall>
    </partial>
    <partial label="rotwfck" calls="1">
      <cpu>2.193739999999997e-1</cpu>
      <wall>2.233719825744629e-1</wall>
    </partial>
    <partial label="rotwfck:hpsi" calls="1">
      <cpu>1.946460000000001e-1</cpu>
      <wall>1.985390186309814e-1</wall>
    </partial>
    <partial label="h_psi_bgrp" calls="64">
      <cpu>4.647835999999991e0</cpu>
      <wall>4.676387786865234e0</wall>
    </partial>
    <partial label="h_psi" calls="64">
      <cpu>4.647725000000001e0</cpu>
      <wall>4.676304340362549e0</wall>
    </partial>
    <partial label="h_psi:pot" calls="64">
      <cpu>4.629042999999994e0</cpu>
      <wall>4.653969287872314e0</wall>
    </partial>
    <partial label="vloc_psi" calls="64">
      <cpu>4.148910000000003e0</cpu>
      <wall>4.165866851806641e0</wall>
    </partial>
    <partial label="fftw" calls="2073">
      <cpu>4.474738000000016e0</cpu>
      <wall>4.489672183990479e0</wall>
    </partial>
    <partial label="h_psi:calbec" calls="64">
      <cpu>2.356669999999959e-1</cpu>
      <wall>2.358601093292236e-1</wall>
    </partial>
    <partial label="calbec" calls="73">
      <cpu>3.007379999999955e-1</cpu>
      <wall>3.010957241058350e-1</wall>
    </partial>
    <partial label="add_vuspsi" calls="64">
      <cpu>2.440820000000059e-1</cpu>
      <wall>2.520148754119873e-1</wall>
    </partial>
    <partial label="rotwfck:hc" calls="1">
      <cpu>1.797099999999974e-2</cpu>
      <wall>1.807713508605957e-2</wall>
    </partial>
    <partial label="s_psi_bgrp" calls="64">
      <cpu>2.633989999999979e-1</cpu>
      <wall>2.674884796142578e-1</wall>
    </partial>
    <partial label="s_psi" calls="64">
      <cpu>2.392729999999972e-1</cpu>
      <wall>2.424662113189697e-1</wall>
    </partial>
    <partial label="rotwfck:diag" calls="1">
      <cpu>1.450000000000173e-3</cpu>
      <wall>1.451015472412109e-3</wall>
    </partial>
    <partial label="cdiaghg" calls="63">
      <cpu>6.571100000000740e-2</cpu>
      <wall>6.661462783813477e-2</wall>
    </partial>
    <partial label="rotwfck:evc" calls="1">
      <cpu>5.138999999999783e-3</cpu>
      <wall>5.142927169799805e-3</wall>
    </partial>
    <partial label="electrons" calls="1">
      <cpu>1.113785100000000e1</cpu>
      <wall>1.146580505371094e1</wall>
    </partial>
    <partial label="c_bands" calls="9">
      <cpu>5.787491999999999e0</cpu>
      <wall>5.821223258972168e0</wall>
    </partial>
    <partial label="cegterg" calls="9">
      <cpu>5.696232999999999e0</cpu>
      <wall>5.727349519729614e0</wall>
    </partial>
    <partial label="cegterg:init" calls="9">
      <cpu>6.384999999999863e-2</cpu>
      <wall>6.387615203857422e-2</wall>
    </partial>
    <partial label="cegterg:upda" calls="54">
      <cpu>1.751199999999997e-1</cpu>
      <wall>1.753101348876953e-1</wall>
    </partial>
    <partial label="g_psi" calls="54">
      <cpu>2.166400000000479e-2</cpu>
      <wall>2.167820930480957e-2</wall>
    </partial>
    <partial label="cegterg:over" calls="54">
      <cpu>3.128789999999970e-1</cpu>
      <wall>3.130233287811279e-1</wall>
    </partial>
    <partial label="cegterg:diag" calls="62">
      <cpu>6.441399999999575e-2</cpu>
      <wall>6.528639793395996e-2</wall>
    </partial>
    <partial label="cegterg:last" calls="22">
      <cpu>3.318989999999999e-1</cpu>
      <wall>3.319716453552246e-1</wall>
    </partial>
    <partial label="sum_band" calls="9">
      <cpu>1.523782000000001e0</cpu>
      <wall>1.665562152862549e0</wall>
    </partial>
    <partial label="sum_band:wei" calls="9">
      <cpu>3.399999999764702e-5</cpu>
      <wall>3.457069396972656e-5</wall>
    </partial>
    <partial label="sum_band:loo" calls="9">
      <cpu>7.814040000000002e-1</cpu>
      <wall>7.850465774536133e-1</wall>
    </partial>
    <partial label="sum_band:buf" calls="9">
      <cpu>2.999999999531155e-6</cpu>
      <wall>3.099441528320313e-6</wall>
    </partial>
    <partial label="sum_band:ini" calls="9">
      <cpu>2.500699999999867e-2</cpu>
      <wall>2.812385559082031e-2</wall>
    </partial>
    <partial label="sum_band:cal" calls="9">
      <cpu>6.545400000000079e-2</cpu>
      <wall>6.545281410217285e-2</wall>
    </partial>
    <partial label="sum_band:bec" calls="9">
      <cpu>3.540000000015198e-4</cpu>
      <wall>3.552436828613281e-4</wall>
    </partial>
    <partial label="ffts" calls="9">
      <cpu>2.023600000000059e-2</cpu>
      <wall>2.023386955261230e-2</wall>
    </partial>
    <partial label="addusdens" calls="9">
      <cpu>6.563240000000032e-1</cpu>
      <wall>7.902128696441650e-1</wall>
    </partial>
    <partial label="addusd:skk" calls="36">
      <cpu>2.282500000000454e-2</cpu>
      <wall>2.515411376953125e-2</wall>
    </partial>
    <partial label="addusd:dgemm" calls="36">
      <cpu>1.274120000000014e-1</cpu>
      <wall>2.455978393554688e-1</wall>
    </partial>
    <partial label="addusd:qvan2" calls="36">
      <cpu>4.177169999999961e-1</cpu>
      <wall>4.309673309326172e-1</wall>
    </partial>
    <partial label="sum_band:sym" calls="9">
      <cpu>5.757599999999918e-2</cpu>
      <wall>6.158614158630371e-2</wall>
    </partial>
    <partial label="mix_rho" calls="9">
      <cpu>8.770299999999942e-2</cpu>
      <wall>9.860301017761230e-2</wall>
    </partial>
    <partial label="ions" calls="1">
      <cpu>9.999999992515995e-7</cpu>
      <wall>1.192092895507813e-6</wall>
    </partial>
  </timing_info>
  <closed DATE="20 Oct 2022" TIME="17:22:39"></closed>
</qes:espresso>
